{
  "learning_enabled": true,
  "prediction_enabled": true,
  "enhanced_features_enabled": true,
  "learning_rate": 0.01,
  "confidence_threshold": 0.6,
  "pattern_memory_size": 1000,
  "prediction_horizon": 300,
  "optimization_level": "adaptive",
  "auto_optimization_enabled": true,
  "proactive_optimization": true,
  "prediction_interval": 10000,
  "monitoring_interval": 2000,
  "resource_check_interval": 5000,
  "enhanced_ml_enabled": true,
  "intelligent_monitoring_enabled": true,
  "smart_resources_enabled": true,
  "adaptive_thresholds_enabled": true,
  "anomaly_detection_enabled": true,
  "max_memory_mb": 1024,
  "cache_size_mb": 256,
  "gc_threshold": 0.85,
  "emergency_threshold": 0.95,
  "max_cpu_usage": 80.0,
  "cpu_optimization_enabled": true,
  "dynamic_scheduling": true,
  "deep_learning_enabled": true,
  "ensemble_predictions": true,
  "multi_model_training": true,
  "real_time_adaptation": true,
  "performance_alerts_enabled": true,
  "resource_alerts_enabled": true,
  "prediction_accuracy_alerts": true,
  "alert_threshold": 0.8,
  "analytics_enabled": true,
  "detailed_logging": true,
  "metrics_retention_days": 30,
  "export_enabled": true
}